k_pass/__init__.py
k_pass/random_password.py
k_pass-0.0.2.dist-info/LICENSE
k_pass-0.0.2.dist-info/METADATA
k_pass-0.0.2.dist-info/WHEEL
k_pass-0.0.2.dist-info/top_level.txt
k_pass-0.0.2.dist-info/RECORD
