Metadata-Version: 2.1
Name: k-pass
Version: 0.0.2
Summary: Python package to generate random strong password and OTP.
Home-page: https://github.com/wskoly/k_pass/
Author: Wahid Sadique Koly
Author-email: wskoly.bp@gmail.com
License: MIT
Keywords: python,password,random,Random password,OTP
Platform: UNKNOWN
Classifier: Development Status :: 4 - Beta
Classifier: Intended Audience :: Developers
Classifier: Programming Language :: Python :: 3
Classifier: Operating System :: Unix
Classifier: Operating System :: MacOS :: MacOS X
Classifier: Operating System :: Microsoft :: Windows
